{
  "completions": [
    {
      "created_at": 1600788040,
      "id": 290001,
      "lead_time": 36.158,
      "result": [
        {
          "from_name": "label",
          "id": "qXK09dLkif",
          "parent_id": null,
          "source": "$text",
          "to_name": "text",
          "type": "labels",
          "value": {
            "end": 34,
            "labels": [
              "Positive",
              "Food"
            ],
            "start": 14,
            "text": "dimsum disini juarak"
          }
        },
        {
          "from_name": "label",
          "id": "uF1agBvcp-",
          "parent_id": null,
          "source": "$text",
          "to_name": "text",
          "type": "labels",
          "value": {
            "end": 130,
            "labels": [
              "Positive",
              "Food"
            ],
            "start": 90,
            "text": "menunya banyak bgt sampe pusing milihnya"
          }
        },
        {
          "from_name": "label",
          "id": "fN7NTVXSGy",
          "parent_id": null,
          "source": "$text",
          "to_name": "text",
          "type": "labels",
          "value": {
            "end": 148,
            "labels": [
              "Positive",
              "Food"
            ],
            "start": 131,
            "text": "rasanya enak bgtt"
          }
        },
        {
          "from_name": "label",
          "id": "9mpJ0QMF_2",
          "parent_id": null,
          "source": "$text",
          "to_name": "text",
          "type": "labels",
          "value": {
            "end": 161,
            "labels": [
              "Positive",
              "Ambience"
            ],
            "start": 150,
            "text": "tempat gede"
          }
        },
        {
          "from_name": "label",
          "id": "R0hzzg7kMz",
          "parent_id": null,
          "source": "$text",
          "to_name": "text",
          "type": "labels",
          "value": {
            "end": 188,
            "labels": [
              "Positive",
              "Service"
            ],
            "start": 163,
            "text": "pelayan banyak dan gercep"
          }
        },
        {
          "from_name": "label",
          "id": "POtO9YJ5cT",
          "parent_id": null,
          "source": "$text",
          "to_name": "text",
          "type": "labels",
          "value": {
            "end": 242,
            "labels": [
              "Positive",
              "Miscellaneous"
            ],
            "start": 217,
            "text": "lain kali bakal balik lgi"
          }
        }
      ]
    }
  ],
  "data": {
    "text": "wah gila sih. dimsum disini juarak. kalo hari biasa all you can eat, tp hr ini ala carte. menunya banyak bgt sampe pusing milihnya rasanya enak bgtt. tempat gede, pelayan banyak dan gercep. habis 300 rb an worth bgt. lain kali bakal balik lgi.   selamat mencoba!"
  },
  "id": 290
}